<project
xsi:schemaLocation="http://maven.apache.org/POM/4.0.0 http://maven.apache.org/xsd/maven-4.0.0.xsd" xmlns="http://maven.apache.org/POM/4.0.0" xmlns:xsi="http://www.w3.org/2001/XMLSchema-instance">
	<modelVersion>4.0.0</modelVersion>
	<groupId>org.jboss.tools</groupId>
	<artifactId>bootstrap</artifactId>
	<version>0.0.1-SNAPSHOT</version>
	<packaging>pom</packaging>
	<scm>
		<connection>scm:svn:https://anonsvn.jboss.org/repos/jbosstools/trunk</connection>
		<developerConnection>scm:svn:https://svn.jboss.org/repos/jbosstools/trunk</developerConnection>
		<url>https://anonsvn.jboss.org/repos/jbosstools/trunk</url>
	</scm>
	<properties>

	</properties>
	<build>
		<plugins>
			<plugin>
				<groupId>org.apache.maven.plugins</groupId>
				<artifactId>maven-scm-plugin</artifactId>
				<version>1.3</version>
				<configuration>
					<checkoutDirectory>${basedir}/sources</checkoutDirectory>
					<goals>clean,install</goals>
					<profiles>helios-no-target</profiles>
				</configuration>
			</plugin>
		</plugins>
	</build>
</project>
